<?xml version="1.0" encoding="UTF-8"?>
<ti:work xmlns:cpt="http://purl.org/capitains/ns/1.0#" xmlns:dc="http://purl.org/dc/elements/1.1/"
    xmlns:dct="http://purl.org/dc/terms/" xmlns:ti="http://chs.harvard.edu/xmlns/cts" xmlns:rdf="http://www.w3.org/1999/02/22-rdf-syntax-ns#"
    groupUrn="urn:cts:freLit:pos2002" projid="freLit:pos200227"
    urn="urn:cts:freLit:pos2002.pos200227" xml:lang="fre"> 
    <ti:title xml:lang="fre">Les ingénieurs géographes des camps et armées du roi, de la guerre_de_Sept_Ans à la Révolution (1756-1791) : étude institutionnelle, prosopographique et sociale</ti:title>
    <ti:edition workUrn="urn:cts:freLit:pos2002.pos200227" urn="urn:cts:freLit:pos2002.pos200227.posENC">
        <ti:label xml:lang="fre"><title type="main">Les ingénieurs géographes des camps et armées du roi, de la guerre_de_Sept_Ans à la Révolution (1756-1791) : étude institutionnelle, prosopographique et sociale</title></ti:label>
        <ti:description xml:lang="fre">
            <p>Positions des thèses soutenues par Patrice Ract pour obtenir le diplôme d’archiviste paléographe</p>		
        </ti:description>
    </ti:edition>
    <cpt:structured-metadata>
        <dc:publisher xml:lang="fre">École nationale des Chartes</dc:publisher>
        <dc:date rdf:datatype="xsd:gYear">2002</dc:date>
        <dct:isVersionOf xml:lang="fre">http://www.sudoc.fr/149849036</dct:isVersionOf> 
        <dc:creator xml:lang="fre">Patrice Ract</dc:creator>
        <dc:creator xml:lang="fre">https://www.idref.fr/076081885</dc:creator>
    </cpt:structured-metadata>
</ti:work>